icdanalysis/__init__.py
icdanalysis/estimation.py
icdanalysis/preprocessing.py
icdanalysis/resolve_chapters.py
icdanalysis/table1.py
icd_att_tools-0.1.0.dist-info/METADATA
icd_att_tools-0.1.0.dist-info/WHEEL
icd_att_tools-0.1.0.dist-info/entry_points.txt
icd_att_tools-0.1.0.dist-info/top_level.txt
icd_att_tools-0.1.0.dist-info/RECORD
